Metadata-Version: 2.1
Name: dataset-shuffler
Version: 0.1.1
Summary: Data engineering tool for learning-based computer vision.
Author-email: Evgeny Toropov <toropov.evgeny@gmail.com>
License: MIT License
Project-URL: Homepage, https://github.com/kukuruza/shuffler
Keywords: dataset,data engineering,computer vision,machine learning,classification,detection,segmentation,tracking
Classifier: License :: OSI Approved :: MIT License
Classifier: Programming Language :: Python
Classifier: Programming Language :: Python :: 3
Requires-Python: >=3.6
License-File: LICENSE
Requires-Dist: imageio (>=2.5.0)
Requires-Dist: imageio-ffmpeg (>=0.2.0)
Requires-Dist: opencv-python (>=3.1.0.5)
Requires-Dist: matplotlib (>=2.0)
Requires-Dist: progressbar2 (>=3.37.1)
Requires-Dist: lxml
Requires-Dist: simplejson
Requires-Dist: pillow
Provides-Extra: ml
Requires-Dist: scikit-learn ; extra == 'ml'
Requires-Dist: torch (>=1.0.0) ; extra == 'ml'
Requires-Dist: tensorflow (>=2.0) ; extra == 'ml'
Provides-Extra: plots
Requires-Dist: pandas ; extra == 'plots'
Requires-Dist: seaborn ; extra == 'plots'
Provides-Extra: test
Requires-Dist: mock ; extra == 'test'
Requires-Dist: nose ; extra == 'test'
